pyqt_finance/__init__.py
pyqt_finance/widget.py
pyqt_finance-0.0.1.dist-info/DESCRIPTION.rst
pyqt_finance-0.0.1.dist-info/METADATA
pyqt_finance-0.0.1.dist-info/RECORD
pyqt_finance-0.0.1.dist-info/WHEEL
pyqt_finance-0.0.1.dist-info/metadata.json
pyqt_finance-0.0.1.dist-info/top_level.txt
