Metadata-Version: 2.0
Name: pyqt-finance
Version: 0.0.1
Summary: Custom QWidget for display historical stock data
Home-page: https://github.com/AndrewRPorter/pyqt-finance
Author: Andrew Porter
Author-email: porter.r.andrew@gmail.com
License: MIT License
Requires-Dist: matplotlib
Requires-Dist: pandas
Requires-Dist: requests
Requires-Dist: setuptools
Requires-Dist: yahoo-historical
